[{"fullname": "\u3057\u308d\u3053\u3064\u305f\u3053", "html": "<p class=\"TweetTextSize js-tweet-text tweet-text\" data-aria-label-part=\"0\" lang=\"ja\">\u6700\u8fd1\u65b0\u3057\u3044\u30a2\u30d7\u30ea\u59cb\u3081\u3066\u307f\u305f\n\u4e00\u679a\u306e\u7d75\u306e\u4e2d\u304b\u3089\u3001\u30ea\u30b9\u30c8\u306b\u3042\u308b\u3082\u306e\u3092\u898b\u3064\u3051\u3066\u3044\u304f\u30b2\u30fc\u30e0\u306a\u3093\u3060\u3051\u3069\u4e2d\u3005\u9762\u767d\u3044\u30fc\n\u3064\u3044\u3064\u3044\u3084\u3063\u3066\u3057\u307e\u3046\uff01\n\u305f\u3060\u82f1\u8a9e\u3067\u805e\u304b\u308c\u308b\u3068\u30e4\u30de\u30ab\u30f3\u306e\u6642\u304c\u591a\u3044w\n<a class=\"twitter-hashtag pretty-link js-nav\" data-query-source=\"hashtag_click\" dir=\"ltr\" href=\"/hashtag/AliceintheMirrorsofAlbion?src=hash\"><s>#</s><b><strong>AliceintheMirrorsofAlbion</strong></b></a></p>", "id": "836781476393840640", "likes": "0", "replies": "0", "retweets": "0", "text": "\u6700\u8fd1\u65b0\u3057\u3044\u30a2\u30d7\u30ea\u59cb\u3081\u3066\u307f\u305f\n\u4e00\u679a\u306e\u7d75\u306e\u4e2d\u304b\u3089\u3001\u30ea\u30b9\u30c8\u306b\u3042\u308b\u3082\u306e\u3092\u898b\u3064\u3051\u3066\u3044\u304f\u30b2\u30fc\u30e0\u306a\u3093\u3060\u3051\u3069\u4e2d\u3005\u9762\u767d\u3044\u30fc\n\u3064\u3044\u3064\u3044\u3084\u3063\u3066\u3057\u307e\u3046\uff01\n\u305f\u3060\u82f1\u8a9e\u3067\u805e\u304b\u308c\u308b\u3068\u30e4\u30de\u30ab\u30f3\u306e\u6642\u304c\u591a\u3044w\n#AliceintheMirrorsofAlbion", "timestamp": "2017-03-01T03:33:45", "url": "/shirokotsutako/status/836781476393840640", "user": "shirokotsutako"}, {"fullname": "Samsung Galaxy Apps Store", "html": "<p class=\"TweetTextSize js-tweet-text tweet-text\" data-aria-label-part=\"0\" lang=\"en\">Can you foil the evil schemes of the Queen of Hearts and save the city of Albion? Put your skills to the test in <a class=\"twitter-hashtag pretty-link js-nav\" data-query-source=\"hashtag_click\" dir=\"ltr\" href=\"/hashtag/AliceInTheMirrorsOfAlbion?src=hash\"><s>#</s><b><strong>AliceInTheMirrorsOfAlbion</strong></b></a> by <a class=\"twitter-atreply pretty-link js-nav\" data-mentioned-user-id=\"377385039\" dir=\"ltr\" href=\"/Game_Insight\"><s>@</s><b>Game_Insight</b></a>: <a class=\"twitter-timeline-link\" data-expanded-url=\"http://bit.ly/30AliceintheMirrorsofAlbion\" dir=\"ltr\" href=\"https://t.co/eSWBZs5NL3\" rel=\"nofollow noopener\" target=\"_blank\" title=\"http://bit.ly/30AliceintheMirrorsofAlbion\"><span class=\"tco-ellipsis\"></span><span class=\"invisible\">http://</span><span class=\"js-display-url\">bit.ly/30AliceintheMi</span><span class=\"invisible\">rrorsofAlbion</span><span class=\"tco-ellipsis\"><span class=\"invisible\">\u00a0</span>\u2026</span></a> <img alt=\"\ud83c\udff0\" aria-label=\"Emoji: European castle\" class=\"Emoji Emoji--forText\" draggable=\"false\" src=\"https://abs.twimg.com/emoji/v2/72x72/1f3f0.png\" title=\"European castle\"/> <a class=\"twitter-hashtag pretty-link js-nav\" data-query-source=\"hashtag_click\" dir=\"ltr\" href=\"/hashtag/MirrorsOfAlbion?src=hash\"><s>#</s><b>MirrorsOfAlbion</b></a><a class=\"twitter-timeline-link u-hidden\" data-pre-embedded=\"true\" dir=\"ltr\" href=\"https://t.co/vfix5vgDpx\">pic.twitter.com/vfix5vgDpx</a></p>", "id": "979901221879386113", "likes": "0", "replies": "0", "retweets": "0", "text": "Can you foil the evil schemes of the Queen of Hearts and save the city of Albion? Put your skills to the test in #AliceInTheMirrorsOfAlbion by @Game_Insight: http://bit.ly/30AliceintheMirrorsofAlbion\u00a0\u2026  #MirrorsOfAlbionpic.twitter.com/vfix5vgDpx", "timestamp": "2018-03-31T02:00:31", "url": "/GalaxyAppsStore/status/979901221879386113", "user": "GalaxyAppsStore"}]